widit/__init__.py
widit/blocks.py
widit/models.py
widit/patch.py
widit/timesteps.py
widit/window.py
widit-0.1.0a1.dist-info/LICENSE
widit-0.1.0a1.dist-info/METADATA
widit-0.1.0a1.dist-info/WHEEL
widit-0.1.0a1.dist-info/RECORD
