Metadata-Version: 2.3
Name: WiDiT
Version: 0.1.0a1
Summary: Windowed Diffusion Transformer in 2D and 3D
License: Apache-2.0
Keywords: torchapp,pytorch,deep learning,command-line interface
Author: Robert Turnbull
Author-email: robert.turnbull@unimelb.edu.au
Requires-Python: >=3.10,<3.14
Classifier: Intended Audience :: Science/Research
Classifier: License :: OSI Approved :: Apache Software License
Classifier: Programming Language :: Python :: 3
Classifier: Programming Language :: Python :: 3.10
Classifier: Programming Language :: Python :: 3.11
Classifier: Programming Language :: Python :: 3.12
Classifier: Programming Language :: Python :: 3.13
Classifier: Topic :: Scientific/Engineering :: Artificial Intelligence
Classifier: Topic :: Software Development :: Libraries :: Python Modules
Requires-Dist: timm (>=1.0.19)
Requires-Dist: torch (>=2.2.0)
Project-URL: Documentation, https://rbturnbull.github.io/widit
Project-URL: Homepage, https://github.com/rbturnbull/widit/
Project-URL: Repository, https://github.com/rbturnbull/widit/
